{
  "source_files": [
    "sample_input/fa_bad_inefficient.hivm.mlir"
  ],
  "source_meta": {
    "files": [],
    "deprecated_ignored_source_files": [],
    "note": "Python/Triton source files are not parsed in V2.7. Use --des-profile/--trace-profile JSON inputs; source-derived ideas are built into templates manually."
  },
  "mlir_evidence": {
    "available": true,
    "file": "sample_input/fa_bad_inefficient.hivm.mlir",
    "num_lines": 68,
    "op_counts": {
      "set_flag": 0,
      "wait_flag": 0,
      "pipe_barrier": 2,
      "sync_block_set": 0,
      "sync_block_wait": 0,
      "nd2nz": 3,
      "mmadL1": 0,
      "mmad": 2,
      "fixpipe": 2,
      "load": 3,
      "store": 1,
      "copy": 0,
      "vreduce": 2,
      "vsub": 1,
      "vexp": 1,
      "vdiv": 1
    },
    "hivm_multi_buffer_annotations": 0,
    "hivm_part_of_mix": 0,
    "hivm_storage_aligned": 0,
    "memrefs_by_space": {
      "gm": 8,
      "l0c": 5,
      "l1": 9,
      "ub": 33
    },
    "static_memref_bytes_by_space": {
      "gm": 1114112,
      "l0c": 40960,
      "l1": 98304,
      "ub": 394752
    },
    "unique_alloc_count_by_space": {
      "ub": 9,
      "l1": 3,
      "l0c": 1
    },
    "unique_alloc_bytes_by_space": {
      "ub": 98816,
      "l1": 32768,
      "l0c": 8192
    },
    "static_max_live_bytes_by_space": {
      "l0a": 0,
      "ub": 98816,
      "l0c": 8192,
      "l0b": 0,
      "l1": 32768
    },
    "sample_memrefs": [
      {
        "shape_body": "64x128xf16,",
        "space": "gm",
        "dims": [
          64,
          128
        ],
        "dtype": "f16",
        "size_bytes_static": 16384
      },
      {
        "shape_body": "1024x128xf16,",
        "space": "gm",
        "dims": [
          1024,
          128
        ],
        "dtype": "f16",
        "size_bytes_static": 262144
      },
      {
        "shape_body": "1024x128xf16,",
        "space": "gm",
        "dims": [
          1024,
          128
        ],
        "dtype": "f16",
        "size_bytes_static": 262144
      },
      {
        "shape_body": "64x128xf16,",
        "space": "gm",
        "dims": [
          64,
          128
        ],
        "dtype": "f16",
        "size_bytes_static": 16384
      },
      {
        "shape_body": "64x128xf16,",
        "space": "ub",
        "dims": [
          64,
          128
        ],
        "dtype": "f16",
        "size_bytes_static": 16384
      },
      {
        "shape_body": "64x128xf32,",
        "space": "ub",
        "dims": [
          64,
          128
        ],
        "dtype": "f32",
        "size_bytes_static": 32768
      },
      {
        "shape_body": "64x32xf32,",
        "space": "ub",
        "dims": [
          64,
          32
        ],
        "dtype": "f32",
        "size_bytes_static": 8192
      },
      {
        "shape_body": "64x32xf32,",
        "space": "ub",
        "dims": [
          64,
          32
        ],
        "dtype": "f32",
        "size_bytes_static": 8192
      },
      {
        "shape_body": "64x1xf32,",
        "space": "ub",
        "dims": [
          64,
          1
        ],
        "dtype": "f32",
        "size_bytes_static": 256
      },
      {
        "shape_body": "64x1xf32,",
        "space": "ub",
        "dims": [
          64,
          1
        ],
        "dtype": "f32",
        "size_bytes_static": 256
      },
      {
        "shape_body": "32x128xf16,",
        "space": "ub",
        "dims": [
          32,
          128
        ],
        "dtype": "f16",
        "size_bytes_static": 8192
      },
      {
        "shape_body": "32x128xf16,",
        "space": "ub",
        "dims": [
          32,
          128
        ],
        "dtype": "f16",
        "size_bytes_static": 8192
      },
      {
        "shape_body": "64x128xf16,",
        "space": "l1",
        "dims": [
          64,
          128
        ],
        "dtype": "f16",
        "size_bytes_static": 16384
      },
      {
        "shape_body": "32x128xf16,",
        "space": "l1",
        "dims": [
          32,
          128
        ],
        "dtype": "f16",
        "size_bytes_static": 8192
      },
      {
        "shape_body": "32x128xf16,",
        "space": "l1",
        "dims": [
          32,
          128
        ],
        "dtype": "f16",
        "size_bytes_static": 8192
      },
      {
        "shape_body": "64x32xf32,",
        "space": "l0c",
        "dims": [
          64,
          32
        ],
        "dtype": "f32",
        "size_bytes_static": 8192
      },
      {
        "shape_body": "64x128xf16,",
        "space": "ub",
        "dims": [
          64,
          128
        ],
        "dtype": "f16",
        "size_bytes_static": 16384
      },
      {
        "shape_body": "64x128xf16,",
        "space": "gm",
        "dims": [
          64,
          128
        ],
        "dtype": "f16",
        "size_bytes_static": 16384
      },
      {
        "shape_body": "64x128xf16,",
        "space": "ub",
        "dims": [
          64,
          128
        ],
        "dtype": "f16",
        "size_bytes_static": 16384
      },
      {
        "shape_body": "64x128xf16,",
        "space": "ub",
        "dims": [
          64,
          128
        ],
        "dtype": "f16",
        "size_bytes_static": 16384
      },
      {
        "shape_body": "64x128xf16,",
        "space": "l1",
        "dims": [
          64,
          128
        ],
        "dtype": "f16",
        "size_bytes_static": 16384
      },
      {
        "shape_body": "1024x128xf16,",
        "space": "gm",
        "dims": [
          1024,
          128
        ],
        "dtype": "f16",
        "size_bytes_static": 262144
      },
      {
        "shape_body": "32x128xf16,",
        "space": "ub",
        "dims": [
          32,
          128
        ],
        "dtype": "f16",
        "size_bytes_static": 8192
      },
      {
        "shape_body": "1024x128xf16,",
        "space": "gm",
        "dims": [
          1024,
          128
        ],
        "dtype": "f16",
        "size_bytes_static": 262144
      },
      {
        "shape_body": "32x128xf16,",
        "space": "ub",
        "dims": [
          32,
          128
        ],
        "dtype": "f16",
        "size_bytes_static": 8192
      },
      {
        "shape_body": "32x128xf16,",
        "space": "ub",
        "dims": [
          32,
          128
        ],
        "dtype": "f16",
        "size_bytes_static": 8192
      },
      {
        "shape_body": "32x128xf16,",
        "space": "l1",
        "dims": [
          32,
          128
        ],
        "dtype": "f16",
        "size_bytes_static": 8192
      },
      {
        "shape_body": "32x128xf16,",
        "space": "ub",
        "dims": [
          32,
          128
        ],
        "dtype": "f16",
        "size_bytes_static": 8192
      },
      {
        "shape_body": "32x128xf16,",
        "space": "l1",
        "dims": [
          32,
          128
        ],
        "dtype": "f16",
        "size_bytes_static": 8192
      },
      {
        "shape_body": "64x128xf16,",
        "space": "l1",
        "dims": [
          64,
          128
        ],
        "dtype": "f16",
        "size_bytes_static": 16384
      }
    ],
    "sample_named_memrefs": [
      {
        "name": "Q_gm",
        "space": "gm",
        "dims": [
          64,
          128
        ],
        "dtype": "f16",
        "size_bytes_static": 16384,
        "line": 12,
        "is_alloc": false
      },
      {
        "name": "K_gm",
        "space": "gm",
        "dims": [
          1024,
          128
        ],
        "dtype": "f16",
        "size_bytes_static": 262144,
        "line": 13,
        "is_alloc": false
      },
      {
        "name": "V_gm",
        "space": "gm",
        "dims": [
          1024,
          128
        ],
        "dtype": "f16",
        "size_bytes_static": 262144,
        "line": 14,
        "is_alloc": false
      },
      {
        "name": "O_gm",
        "space": "gm",
        "dims": [
          64,
          128
        ],
        "dtype": "f16",
        "size_bytes_static": 16384,
        "line": 15,
        "is_alloc": false
      },
      {
        "name": "q_ub",
        "space": "ub",
        "dims": [
          64,
          128
        ],
        "dtype": "f16",
        "size_bytes_static": 16384,
        "line": 20,
        "is_alloc": true
      },
      {
        "name": "acc_ub",
        "space": "ub",
        "dims": [
          64,
          128
        ],
        "dtype": "f32",
        "size_bytes_static": 32768,
        "line": 21,
        "is_alloc": true
      },
      {
        "name": "s_ub",
        "space": "ub",
        "dims": [
          64,
          32
        ],
        "dtype": "f32",
        "size_bytes_static": 8192,
        "line": 22,
        "is_alloc": true
      },
      {
        "name": "p_ub",
        "space": "ub",
        "dims": [
          64,
          32
        ],
        "dtype": "f32",
        "size_bytes_static": 8192,
        "line": 23,
        "is_alloc": true
      },
      {
        "name": "m_ub",
        "space": "ub",
        "dims": [
          64,
          1
        ],
        "dtype": "f32",
        "size_bytes_static": 256,
        "line": 24,
        "is_alloc": true
      },
      {
        "name": "l_ub",
        "space": "ub",
        "dims": [
          64,
          1
        ],
        "dtype": "f32",
        "size_bytes_static": 256,
        "line": 25,
        "is_alloc": true
      },
      {
        "name": "k_ub",
        "space": "ub",
        "dims": [
          32,
          128
        ],
        "dtype": "f16",
        "size_bytes_static": 8192,
        "line": 26,
        "is_alloc": true
      },
      {
        "name": "v_ub",
        "space": "ub",
        "dims": [
          32,
          128
        ],
        "dtype": "f16",
        "size_bytes_static": 8192,
        "line": 27,
        "is_alloc": true
      },
      {
        "name": "q_l1",
        "space": "l1",
        "dims": [
          64,
          128
        ],
        "dtype": "f16",
        "size_bytes_static": 16384,
        "line": 28,
        "is_alloc": true
      },
      {
        "name": "k_l1",
        "space": "l1",
        "dims": [
          32,
          128
        ],
        "dtype": "f16",
        "size_bytes_static": 8192,
        "line": 29,
        "is_alloc": true
      },
      {
        "name": "v_l1",
        "space": "l1",
        "dims": [
          32,
          128
        ],
        "dtype": "f16",
        "size_bytes_static": 8192,
        "line": 30,
        "is_alloc": true
      },
      {
        "name": "s_l0c",
        "space": "l0c",
        "dims": [
          64,
          32
        ],
        "dtype": "f32",
        "size_bytes_static": 8192,
        "line": 31,
        "is_alloc": true
      },
      {
        "name": "o_ub",
        "space": "ub",
        "dims": [
          64,
          128
        ],
        "dtype": "f16",
        "size_bytes_static": 16384,
        "line": 32,
        "is_alloc": true
      },
      {
        "name": "Q_gm",
        "space": "gm",
        "dims": [
          64,
          128
        ],
        "dtype": "f16",
        "size_bytes_static": 16384,
        "line": 36,
        "is_alloc": false
      },
      {
        "name": "q_ub",
        "space": "ub",
        "dims": [
          64,
          128
        ],
        "dtype": "f16",
        "size_bytes_static": 16384,
        "line": 36,
        "is_alloc": false
      },
      {
        "name": "q_ub",
        "space": "ub",
        "dims": [
          64,
          128
        ],
        "dtype": "f16",
        "size_bytes_static": 16384,
        "line": 37,
        "is_alloc": false
      },
      {
        "name": "q_l1",
        "space": "l1",
        "dims": [
          64,
          128
        ],
        "dtype": "f16",
        "size_bytes_static": 16384,
        "line": 37,
        "is_alloc": false
      },
      {
        "name": "K_gm",
        "space": "gm",
        "dims": [
          1024,
          128
        ],
        "dtype": "f16",
        "size_bytes_static": 262144,
        "line": 39,
        "is_alloc": false
      },
      {
        "name": "k_ub",
        "space": "ub",
        "dims": [
          32,
          128
        ],
        "dtype": "f16",
        "size_bytes_static": 8192,
        "line": 39,
        "is_alloc": false
      },
      {
        "name": "V_gm",
        "space": "gm",
        "dims": [
          1024,
          128
        ],
        "dtype": "f16",
        "size_bytes_static": 262144,
        "line": 40,
        "is_alloc": false
      },
      {
        "name": "v_ub",
        "space": "ub",
        "dims": [
          32,
          128
        ],
        "dtype": "f16",
        "size_bytes_static": 8192,
        "line": 40,
        "is_alloc": false
      },
      {
        "name": "k_ub",
        "space": "ub",
        "dims": [
          32,
          128
        ],
        "dtype": "f16",
        "size_bytes_static": 8192,
        "line": 41,
        "is_alloc": false
      },
      {
        "name": "k_l1",
        "space": "l1",
        "dims": [
          32,
          128
        ],
        "dtype": "f16",
        "size_bytes_static": 8192,
        "line": 41,
        "is_alloc": false
      },
      {
        "name": "v_ub",
        "space": "ub",
        "dims": [
          32,
          128
        ],
        "dtype": "f16",
        "size_bytes_static": 8192,
        "line": 42,
        "is_alloc": false
      },
      {
        "name": "v_l1",
        "space": "l1",
        "dims": [
          32,
          128
        ],
        "dtype": "f16",
        "size_bytes_static": 8192,
        "line": 42,
        "is_alloc": false
      },
      {
        "name": "k_l1",
        "space": "l1",
        "dims": [
          64,
          128
        ],
        "dtype": "f16",
        "size_bytes_static": 16384,
        "line": 47,
        "is_alloc": false
      },
      {
        "name": "s_l0c",
        "space": "l0c",
        "dims": [
          64,
          32
        ],
        "dtype": "f32",
        "size_bytes_static": 8192,
        "line": 47,
        "is_alloc": false
      },
      {
        "name": "s_l0c",
        "space": "l0c",
        "dims": [
          64,
          32
        ],
        "dtype": "f32",
        "size_bytes_static": 8192,
        "line": 48,
        "is_alloc": false
      },
      {
        "name": "s_ub",
        "space": "ub",
        "dims": [
          64,
          32
        ],
        "dtype": "f32",
        "size_bytes_static": 8192,
        "line": 48,
        "is_alloc": false
      },
      {
        "name": "s_ub",
        "space": "ub",
        "dims": [
          64,
          32
        ],
        "dtype": "f32",
        "size_bytes_static": 8192,
        "line": 49,
        "is_alloc": false
      },
      {
        "name": "m_ub",
        "space": "ub",
        "dims": [
          64,
          1
        ],
        "dtype": "f32",
        "size_bytes_static": 256,
        "line": 49,
        "is_alloc": false
      },
      {
        "name": "m_ub",
        "space": "ub",
        "dims": [
          64,
          32
        ],
        "dtype": "f32",
        "size_bytes_static": 8192,
        "line": 50,
        "is_alloc": false
      },
      {
        "name": "p_ub",
        "space": "ub",
        "dims": [
          64,
          32
        ],
        "dtype": "f32",
        "size_bytes_static": 8192,
        "line": 50,
        "is_alloc": false
      },
      {
        "name": "p_ub",
        "space": "ub",
        "dims": [
          64,
          32
        ],
        "dtype": "f32",
        "size_bytes_static": 8192,
        "line": 51,
        "is_alloc": false
      },
      {
        "name": "p_ub",
        "space": "ub",
        "dims": [
          64,
          32
        ],
        "dtype": "f32",
        "size_bytes_static": 8192,
        "line": 52,
        "is_alloc": false
      },
      {
        "name": "l_ub",
        "space": "ub",
        "dims": [
          64,
          1
        ],
        "dtype": "f32",
        "size_bytes_static": 256,
        "line": 52,
        "is_alloc": false
      },
      {
        "name": "v_l1",
        "space": "ub",
        "dims": [
          64,
          32
        ],
        "dtype": "f32",
        "size_bytes_static": 8192,
        "line": 55,
        "is_alloc": false
      },
      {
        "name": "s_l0c",
        "space": "l0c",
        "dims": [
          64,
          32
        ],
        "dtype": "f32",
        "size_bytes_static": 8192,
        "line": 55,
        "is_alloc": false
      },
      {
        "name": "s_l0c",
        "space": "l0c",
        "dims": [
          64,
          32
        ],
        "dtype": "f32",
        "size_bytes_static": 8192,
        "line": 56,
        "is_alloc": false
      },
      {
        "name": "acc_ub",
        "space": "ub",
        "dims": [
          64,
          128
        ],
        "dtype": "f32",
        "size_bytes_static": 32768,
        "line": 56,
        "is_alloc": false
      },
      {
        "name": "l_ub",
        "space": "ub",
        "dims": [
          64,
          128
        ],
        "dtype": "f32",
        "size_bytes_static": 32768,
        "line": 62,
        "is_alloc": false
      },
      {
        "name": "acc_ub",
        "space": "ub",
        "dims": [
          64,
          128
        ],
        "dtype": "f32",
        "size_bytes_static": 32768,
        "line": 62,
        "is_alloc": false
      },
      {
        "name": "acc_ub",
        "space": "ub",
        "dims": [
          64,
          128
        ],
        "dtype": "f32",
        "size_bytes_static": 32768,
        "line": 63,
        "is_alloc": false
      },
      {
        "name": "o_ub",
        "space": "ub",
        "dims": [
          64,
          128
        ],
        "dtype": "f16",
        "size_bytes_static": 16384,
        "line": 63,
        "is_alloc": false
      },
      {
        "name": "o_ub",
        "space": "ub",
        "dims": [
          64,
          128
        ],
        "dtype": "f16",
        "size_bytes_static": 16384,
        "line": 64,
        "is_alloc": false
      },
      {
        "name": "O_gm",
        "space": "gm",
        "dims": [
          64,
          128
        ],
        "dtype": "f16",
        "size_bytes_static": 16384,
        "line": 64,
        "is_alloc": false
      }
    ],
    "max_pointer_offset_hint": null,
    "has_cube_ops": true,
    "has_vector_or_fix_ops": true,
    "generic_hivm_structure": {
      "detected": true,
      "logical_axes": [
        "axis_m",
        "axis_n",
        "axis_k"
      ],
      "candidate_tiles_from_cube_ops": [
        {
          "tile_m": 64,
          "tile_n": 32,
          "tile_k": 128
        },
        {
          "tile_m": 64,
          "tile_n": 32,
          "tile_k": 32
        }
      ],
      "primary_tile_candidate": {
        "tile_m": 64,
        "tile_n": 32,
        "tile_k": 128
      },
      "cube_shape_evidence": [
        {
          "line": 47,
          "shapes": [
            {
              "dims": [
                64,
                128
              ],
              "dtype": "f16",
              "space": "l1",
              "size_bytes": 16384
            },
            {
              "dims": [
                32,
                128
              ],
              "dtype": "f16",
              "space": "l1",
              "size_bytes": 8192
            },
            {
              "dims": [
                64,
                32
              ],
              "dtype": "f32",
              "space": "l0c",
              "size_bytes": 8192
            }
          ],
          "inferred_tile": {
            "tile_m": 64,
            "tile_n": 32,
            "tile_k": 128
          }
        },
        {
          "line": 55,
          "shapes": [
            {
              "dims": [
                64,
                32
              ],
              "dtype": "f32",
              "space": "ub",
              "size_bytes": 8192
            },
            {
              "dims": [
                32,
                128
              ],
              "dtype": "f16",
              "space": "l1",
              "size_bytes": 8192
            },
            {
              "dims": [
                64,
                32
              ],
              "dtype": "f32",
              "space": "l0c",
              "size_bytes": 8192
            }
          ],
          "inferred_tile": {
            "tile_m": 64,
            "tile_n": 32,
            "tile_k": 32
          }
        }
      ],
      "memrefs_by_space_detail": {
        "gm": [
          {
            "name": "Q_gm",
            "dims": [
              64,
              128
            ],
            "dtype": "f16",
            "is_alloc": false,
            "size_bytes_static": 16384
          },
          {
            "name": "K_gm",
            "dims": [
              1024,
              128
            ],
            "dtype": "f16",
            "is_alloc": false,
            "size_bytes_static": 262144
          },
          {
            "name": "V_gm",
            "dims": [
              1024,
              128
            ],
            "dtype": "f16",
            "is_alloc": false,
            "size_bytes_static": 262144
          },
          {
            "name": "O_gm",
            "dims": [
              64,
              128
            ],
            "dtype": "f16",
            "is_alloc": false,
            "size_bytes_static": 16384
          },
          {
            "name": "Q_gm",
            "dims": [
              64,
              128
            ],
            "dtype": "f16",
            "is_alloc": false,
            "size_bytes_static": 16384
          },
          {
            "name": "K_gm",
            "dims": [
              1024,
              128
            ],
            "dtype": "f16",
            "is_alloc": false,
            "size_bytes_static": 262144
          },
          {
            "name": "V_gm",
            "dims": [
              1024,
              128
            ],
            "dtype": "f16",
            "is_alloc": false,
            "size_bytes_static": 262144
          },
          {
            "name": "O_gm",
            "dims": [
              64,
              128
            ],
            "dtype": "f16",
            "is_alloc": false,
            "size_bytes_static": 16384
          }
        ],
        "ub": [
          {
            "name": "q_ub",
            "dims": [
              64,
              128
            ],
            "dtype": "f16",
            "is_alloc": true,
            "size_bytes_static": 16384
          },
          {
            "name": "acc_ub",
            "dims": [
              64,
              128
            ],
            "dtype": "f32",
            "is_alloc": true,
            "size_bytes_static": 32768
          },
          {
            "name": "s_ub",
            "dims": [
              64,
              32
            ],
            "dtype": "f32",
            "is_alloc": true,
            "size_bytes_static": 8192
          },
          {
            "name": "p_ub",
            "dims": [
              64,
              32
            ],
            "dtype": "f32",
            "is_alloc": true,
            "size_bytes_static": 8192
          },
          {
            "name": "m_ub",
            "dims": [
              64,
              1
            ],
            "dtype": "f32",
            "is_alloc": true,
            "size_bytes_static": 256
          },
          {
            "name": "l_ub",
            "dims": [
              64,
              1
            ],
            "dtype": "f32",
            "is_alloc": true,
            "size_bytes_static": 256
          },
          {
            "name": "k_ub",
            "dims": [
              32,
              128
            ],
            "dtype": "f16",
            "is_alloc": true,
            "size_bytes_static": 8192
          },
          {
            "name": "v_ub",
            "dims": [
              32,
              128
            ],
            "dtype": "f16",
            "is_alloc": true,
            "size_bytes_static": 8192
          },
          {
            "name": "o_ub",
            "dims": [
              64,
              128
            ],
            "dtype": "f16",
            "is_alloc": true,
            "size_bytes_static": 16384
          },
          {
            "name": "q_ub",
            "dims": [
              64,
              128
            ],
            "dtype": "f16",
            "is_alloc": false,
            "size_bytes_static": 16384
          },
          {
            "name": "q_ub",
            "dims": [
              64,
              128
            ],
            "dtype": "f16",
            "is_alloc": false,
            "size_bytes_static": 16384
          },
          {
            "name": "k_ub",
            "dims": [
              32,
              128
            ],
            "dtype": "f16",
            "is_alloc": false,
            "size_bytes_static": 8192
          },
          {
            "name": "v_ub",
            "dims": [
              32,
              128
            ],
            "dtype": "f16",
            "is_alloc": false,
            "size_bytes_static": 8192
          },
          {
            "name": "k_ub",
            "dims": [
              32,
              128
            ],
            "dtype": "f16",
            "is_alloc": false,
            "size_bytes_static": 8192
          },
          {
            "name": "v_ub",
            "dims": [
              32,
              128
            ],
            "dtype": "f16",
            "is_alloc": false,
            "size_bytes_static": 8192
          },
          {
            "name": "s_ub",
            "dims": [
              64,
              32
            ],
            "dtype": "f32",
            "is_alloc": false,
            "size_bytes_static": 8192
          },
          {
            "name": "s_ub",
            "dims": [
              64,
              32
            ],
            "dtype": "f32",
            "is_alloc": false,
            "size_bytes_static": 8192
          },
          {
            "name": "m_ub",
            "dims": [
              64,
              1
            ],
            "dtype": "f32",
            "is_alloc": false,
            "size_bytes_static": 256
          },
          {
            "name": "m_ub",
            "dims": [
              64,
              32
            ],
            "dtype": "f32",
            "is_alloc": false,
            "size_bytes_static": 8192
          },
          {
            "name": "p_ub",
            "dims": [
              64,
              32
            ],
            "dtype": "f32",
            "is_alloc": false,
            "size_bytes_static": 8192
          },
          {
            "name": "p_ub",
            "dims": [
              64,
              32
            ],
            "dtype": "f32",
            "is_alloc": false,
            "size_bytes_static": 8192
          },
          {
            "name": "p_ub",
            "dims": [
              64,
              32
            ],
            "dtype": "f32",
            "is_alloc": false,
            "size_bytes_static": 8192
          },
          {
            "name": "l_ub",
            "dims": [
              64,
              1
            ],
            "dtype": "f32",
            "is_alloc": false,
            "size_bytes_static": 256
          },
          {
            "name": "v_l1",
            "dims": [
              64,
              32
            ],
            "dtype": "f32",
            "is_alloc": false,
            "size_bytes_static": 8192
          },
          {
            "name": "acc_ub",
            "dims": [
              64,
              128
            ],
            "dtype": "f32",
            "is_alloc": false,
            "size_bytes_static": 32768
          },
          {
            "name": "l_ub",
            "dims": [
              64,
              128
            ],
            "dtype": "f32",
            "is_alloc": false,
            "size_bytes_static": 32768
          },
          {
            "name": "acc_ub",
            "dims": [
              64,
              128
            ],
            "dtype": "f32",
            "is_alloc": false,
            "size_bytes_static": 32768
          },
          {
            "name": "acc_ub",
            "dims": [
              64,
              128
            ],
            "dtype": "f32",
            "is_alloc": false,
            "size_bytes_static": 32768
          },
          {
            "name": "o_ub",
            "dims": [
              64,
              128
            ],
            "dtype": "f16",
            "is_alloc": false,
            "size_bytes_static": 16384
          },
          {
            "name": "o_ub",
            "dims": [
              64,
              128
            ],
            "dtype": "f16",
            "is_alloc": false,
            "size_bytes_static": 16384
          }
        ],
        "l1": [
          {
            "name": "q_l1",
            "dims": [
              64,
              128
            ],
            "dtype": "f16",
            "is_alloc": true,
            "size_bytes_static": 16384
          },
          {
            "name": "k_l1",
            "dims": [
              32,
              128
            ],
            "dtype": "f16",
            "is_alloc": true,
            "size_bytes_static": 8192
          },
          {
            "name": "v_l1",
            "dims": [
              32,
              128
            ],
            "dtype": "f16",
            "is_alloc": true,
            "size_bytes_static": 8192
          },
          {
            "name": "q_l1",
            "dims": [
              64,
              128
            ],
            "dtype": "f16",
            "is_alloc": false,
            "size_bytes_static": 16384
          },
          {
            "name": "k_l1",
            "dims": [
              32,
              128
            ],
            "dtype": "f16",
            "is_alloc": false,
            "size_bytes_static": 8192
          },
          {
            "name": "v_l1",
            "dims": [
              32,
              128
            ],
            "dtype": "f16",
            "is_alloc": false,
            "size_bytes_static": 8192
          },
          {
            "name": "k_l1",
            "dims": [
              64,
              128
            ],
            "dtype": "f16",
            "is_alloc": false,
            "size_bytes_static": 16384
          }
        ],
        "l0c": [
          {
            "name": "s_l0c",
            "dims": [
              64,
              32
            ],
            "dtype": "f32",
            "is_alloc": true,
            "size_bytes_static": 8192
          },
          {
            "name": "s_l0c",
            "dims": [
              64,
              32
            ],
            "dtype": "f32",
            "is_alloc": false,
            "size_bytes_static": 8192
          },
          {
            "name": "s_l0c",
            "dims": [
              64,
              32
            ],
            "dtype": "f32",
            "is_alloc": false,
            "size_bytes_static": 8192
          },
          {
            "name": "s_l0c",
            "dims": [
              64,
              32
            ],
            "dtype": "f32",
            "is_alloc": false,
            "size_bytes_static": 8192
          },
          {
            "name": "s_l0c",
            "dims": [
              64,
              32
            ],
            "dtype": "f32",
            "is_alloc": false,
            "size_bytes_static": 8192
          }
        ]
      },
      "conventional_tensor_signature": {
        "detected": true,
        "Q_gm": [
          64,
          128
        ],
        "K_gm": [
          1024,
          128
        ],
        "V_gm": [
          1024,
          128
        ],
        "O_gm": [
          64,
          128
        ],
        "note": "name-based conventional tensor signature; used as evidence only, not a hard-coded kernel family"
      },
      "loop_trip_annotation": 32
    },
    "ping_pong_pairs": [],
    "event_sync_pairs": [],
    "cv_op_sequence": {
      "num_ops": 19,
      "cube_ops": [
        "mmad",
        "mmad"
      ],
      "vector_ops": [
        "vreduce",
        "vsub",
        "vexp",
        "vreduce",
        "vdiv"
      ],
      "fixpipe_ops": [
        "fixpipe",
        "fixpipe"
      ],
      "layout_ops": [
        "nd2nz",
        "nd2nz",
        "nd2nz"
      ],
      "cv_pipeline_candidate": true,
      "cube_vector_layout_cube_sequence": false,
      "separability_status": "estimated_from_op_sequence",
      "op_sequence_prefix": [
        "load",
        "nd2nz",
        "load",
        "load",
        "nd2nz",
        "nd2nz",
        "barrier",
        "mmad",
        "fixpipe",
        "vreduce",
        "vsub",
        "vexp",
        "vreduce",
        "mmad",
        "fixpipe",
        "barrier",
        "vdiv",
        "cast",
        "store"
      ]
    }
  },
  "des_evidence": {
    "available": false
  },
  "trace_evidence": {
    "available": false,
    "files": [],
    "num_events": 0,
    "top_event_names": []
  },
  "schema_coverage": {
    "has_source_meta": false,
    "has_mlir": true,
    "has_des": false,
    "has_trace": false,
    "parameter_space_evidence": [
      "mlir"
    ],
    "hardware_boundary_evidence": [
      "mlir_address_space"
    ],
    "cost_model_evidence": [],
    "source_input_policy": "Python/Triton source is not accepted as structured input; deprecated --source is ignored."
  }
}